abs_blob_storage_manager_core/repository/blob_storage_manager_repository.py
abs_blob_storage_manager_core/schema/blob_storage_model.py
abs_blob_storage_manager_core/schema/blob_storage_schema.py
abs_blob_storage_manager_core/service/blob_storage_manager_service.py
abs_blob_storage_manager_core-0.3.0.dist-info/METADATA
abs_blob_storage_manager_core-0.3.0.dist-info/WHEEL
abs_blob_storage_manager_core-0.3.0.dist-info/RECORD
