Metadata-Version: 2.3
Name: abs-blob-storage-manager-core
Version: 0.3.0
Summary: Core utilities for managing blob storage operations with support for various cloud providers and local storage systems
License: MIT
Author: AutoBridgeSystems
Author-email: info@autobridgesystems.com
Requires-Python: >=3.11,<4.0
Classifier: License :: OSI Approved :: MIT License
Classifier: Programming Language :: Python :: 3
Classifier: Programming Language :: Python :: 3.11
Classifier: Programming Language :: Python :: 3.12
Classifier: Programming Language :: Python :: 3.13
Requires-Dist: abs-nosql-repository-core (>=0.11.2,<0.12.0)
Requires-Dist: azure-storage-blob (>=12.25.1,<13.0.0)
Requires-Dist: fastapi (>=0.95.0,<2.0.0)
Requires-Dist: pydantic (>=2.0.0,<3.0.0)
